japanAirAnalytics/__init__.py
japanAirAnalytics/ETL/__init__.py
japanAirAnalytics/ETL/config.py
japanAirAnalytics/ETL/createDataFrame.py
japanAirAnalytics/analytics/__init__.py
japanAirAnalytics/store/__init__.py
japanAirAnalytics/store/config.py
japanAirAnalytics/store/newHourlyDataFormat.py
japanAirAnalytics/store/oldHourlyDataFormat.py
japanAirAnalytics/store/stationInfo.py
japanAirAnalytics/store/unZipAirPollution.py
japanAirAnalytics-2023.11.15.1.dist-info/LICENSE
japanAirAnalytics-2023.11.15.1.dist-info/METADATA
japanAirAnalytics-2023.11.15.1.dist-info/WHEEL
japanAirAnalytics-2023.11.15.1.dist-info/top_level.txt
japanAirAnalytics-2023.11.15.1.dist-info/RECORD
